twon_ranker/__init__.py
twon_ranker/api/__init__.py
twon_ranker/api/__main__.py
twon_ranker/api/config.py
twon_ranker/api/docs/index.md
twon_ranker/api/docs/rank.md
twon_ranker/modules/__init__.py
twon_ranker/modules/decay.py
twon_ranker/modules/engagement.py
twon_ranker/modules/noise.py
twon_ranker/post.py
twon_ranker/request.py
twon_ranker/response.py
twon_ranker-0.0.6.dist-info/LICENSE
twon_ranker-0.0.6.dist-info/METADATA
twon_ranker-0.0.6.dist-info/WHEEL
twon_ranker-0.0.6.dist-info/RECORD
