Metadata-Version: 2.1
Name: TWON-Ranker
Version: 0.0.6
Summary: 
Home-page: https://ranker.twon.unit-trier.de
License: Apache-2.0
Author: Simon Münker
Author-email: muenker@uni-trier.de
Requires-Python: >=3.10,<4.0
Classifier: Development Status :: 3 - Alpha
Classifier: Intended Audience :: Developers
Classifier: License :: OSI Approved :: Apache Software License
Classifier: License :: OSI Approved :: MIT License
Classifier: Programming Language :: Python :: 3
Classifier: Programming Language :: Python :: 3.10
Classifier: Programming Language :: Python :: 3.11
Classifier: Programming Language :: Python :: 3.12
Classifier: Topic :: Scientific/Engineering :: Artificial Intelligence
Requires-Dist: fastapi (>=0.112.0,<0.113.0)
Requires-Dist: gunicorn (>=22.0.0,<23.0.0)
Requires-Dist: pydantic (>=2.8.2,<3.0.0)
Requires-Dist: uvicorn (>=0.30.5,<0.31.0)
Project-URL: Repository, https://github.com/smnmnkr/TWON-Ranker
